iters/__init__.py
iters/async_iters.py
iters/async_utils.py
iters/async_wraps.py
iters/constants.py
iters/iters.py
iters/mapping_view.py
iters/mappings.py
iters/ordered_set.py
iters/py.typed
iters/sequence_view.py
iters/state.py
iters/types.py
iters/typing.py
iters/utils.py
iters/wraps.py
iters-0.17.0.dist-info/LICENSE
iters-0.17.0.dist-info/METADATA
iters-0.17.0.dist-info/WHEEL
iters-0.17.0.dist-info/RECORD
