Metadata-Version: 2.1
Name: iters
Version: 0.17.0
Summary: Composable external iteration.
Home-page: https://github.com/nekitdev/iters
License: MIT
Keywords: python,iter,iterator
Author: nekitdev
Requires-Python: >=3.8
Classifier: Development Status :: 4 - Beta
Classifier: Intended Audience :: Developers
Classifier: License :: OSI Approved :: MIT License
Classifier: Operating System :: OS Independent
Classifier: Programming Language :: Python :: 3
Classifier: Programming Language :: Python :: 3.8
Classifier: Programming Language :: Python :: 3.9
Classifier: Programming Language :: Python :: 3.10
Classifier: Programming Language :: Python :: 3.11
Classifier: Programming Language :: Python :: 3.12
Classifier: Topic :: Utilities
Classifier: Typing :: Typed
Requires-Dist: async-extensions (>=3.1.1)
Requires-Dist: funcs (>=0.10.0)
Requires-Dist: mixed-methods (>=1.1.1)
Requires-Dist: named (>=1.4.2)
Requires-Dist: orderings (>=1.3.2)
Requires-Dist: solus (>=1.2.2)
Requires-Dist: typing-aliases (>=1.10.0)
Requires-Dist: typing-extensions (>=4.10.0)
Requires-Dist: wraps (>=0.9.2)
Project-URL: Chat, https://nekit.dev/chat
Project-URL: Documentation, https://nekitdev.github.io/iters
Project-URL: Issues, https://github.com/nekitdev/iters/issues
Project-URL: Repository, https://github.com/nekitdev/iters
